{
    "jugador_blanco": {
        "user_id": "3b6fa3ba-7393-4526-bac4-fc403456142a",
        "username": "IAMohammed(1)(blanco)"
    },
    "jugador_negro": {
        "user_id": "a8c424f8-3a10-45a7-9bb0-f78584516721",
        "username": "IAJulio(2)(negro)"
    },
    "ganador": null,
    "movimientos": [
        {
            "origen": [
                6,
                4
            ],
            "destino": [
                5,
                4
            ],
            "pieza": "Peon",
            "color": "blanco",
            "captura": null
        },
        {
            "origen": [
                1,
                4
            ],
            "destino": [
                3,
                4
            ],
            "pieza": "Peon",
            "color": "negro",
            "captura": null
        },
        {
            "origen": [
                7,
                3
            ],
            "destino": [
                4,
                6
            ],
            "pieza": "Reina",
            "color": "blanco",
            "captura": null
        }
    ],
    "fecha": "2025-05-17 19:37:30.781231"
}